{{- partial "core/set-env.html" . -}}
{{- $list := .Data.Pages -}}
{{- $length := (len $list) -}}
{
    "content" : "Authors",
    "count" : "{{- $length -}}",
    {{ with .Section }}
    "section" : "{{ . }}",
    {{ end }}
    {{ with eq .Kind  "taxonomy"}}
    "taxonomy" : "{{ $.Data.Singular }}",
    "term" : "{{ $.Data.Term }}",
    {{ end }}
    "items" : [
    {{- range $index, $element := $list -}}
    {
      {{- partial "api/author-profile.html" . -}}
      {{- partial "api/aliases.html" . -}}
      {{- partial "api/file-info.html" . -}}
      {{- partial "api/slug.html" . -}}
    }{{- if ne (add $index 1) $length -}},{{- end -}}
    {{- end -}}
    ]
}